odoo/addons/website_sale_firstname/README.rst
odoo/addons/website_sale_firstname/__init__.py
odoo/addons/website_sale_firstname/__manifest__.py
odoo/addons/website_sale_firstname/controllers/__init__.py
odoo/addons/website_sale_firstname/controllers/main.py
odoo/addons/website_sale_firstname/data/data.xml
odoo/addons/website_sale_firstname/i18n/website_sale_firstname.pot
odoo/addons/website_sale_firstname/readme/CONTRIBUTORS.rst
odoo/addons/website_sale_firstname/readme/CREDITS.rst
odoo/addons/website_sale_firstname/readme/DESCRIPTION.rst
odoo/addons/website_sale_firstname/static/description/icon.png
odoo/addons/website_sale_firstname/static/description/index.html
odoo11_addon_website_sale_firstname-11.0.1.0.0.99.dev5.dist-info/METADATA
odoo11_addon_website_sale_firstname-11.0.1.0.0.99.dev5.dist-info/WHEEL
odoo11_addon_website_sale_firstname-11.0.1.0.0.99.dev5.dist-info/top_level.txt
odoo11_addon_website_sale_firstname-11.0.1.0.0.99.dev5.dist-info/RECORD
